bsci_sap_library/__init__.py
bsci_sap_library-0.0.1.dist-info/METADATA
bsci_sap_library-0.0.1.dist-info/WHEEL
bsci_sap_library-0.0.1.dist-info/top_level.txt
bsci_sap_library-0.0.1.dist-info/RECORD
