Metadata-Version: 2.1
Name: bsci_sap_library
Version: 0.0.1
Summary: This package does nothing.
Classifier: Programming Language :: Python :: 3
Classifier: License :: OSI Approved :: MIT License
Classifier: Operating System :: OS Independent
